pynetio.py
setup.py
pynetio.egg-info/PKG-INFO
pynetio.egg-info/SOURCES.txt
pynetio.egg-info/dependency_links.txt
pynetio.egg-info/top_level.txt