Metadata-Version: 1.1
Name: pynetio
Version: 0.1.9.1
Summary: Binding library for Koukaam netio devices
Home-page: https://github.com/eagleamon/pynetio
Author: Joseph Piron (Joseph Piron)
Author-email: joseph.piron@gmail.com
License: UNKNOWN
Keywords: netio,plug,power,network
Platform: UNKNOWN
Classifier: Programming Language :: Python
Classifier: Development Status :: 3 - Alpha
Classifier: Intended Audience :: Developers
Classifier: License :: OSI Approved :: MIT License
Classifier: Operating System :: OS Independent
Classifier: Programming Language :: Python :: 3.5
Classifier: Topic :: Other/Nonlisted Topic
